{
  "lastRunUtc": "2026-02-21T23:51:41.9613218Z",
  "maxPagesUsed": 120,
  "delayMsUsed": 1400,
  "minIntervalMinutes": 10,
  "retentionDays": 60,
  "maxVisibleScripts": 9600,
  "totalPagesAtSource": 2970,
  "maxDetailLookupsPerRun": 6,
  "detailDelayMs": 1500,
  "detailLookupsTried": 6,
  "detailLookupsSucceeded": 0,
  "maxStaleValidationsPerRun": 120,
  "staleDetailValidationsTried": 120,
  "removedInvalidDetail404Count": 31,
  "maxNewPostsPerAuthorPerRun": 2,
  "unresolvedNewPostQuarantineMinutes": 60,
  "burstBlockedOwnerCount": 33,
  "count": 3371,
  "filteredByKeywordCount": 29,
  "filteredByUserCount": 23,
  "filteredBySpamCount": 161,
  "filteredByOwnerBurstCount": 161,
  "filteredByRunAuthorBurstCount": 161,
  "filteredByUnresolvedNewCount": 0,
  "filteredCount": 213
}
